qtree/__init__.py
qtree/__version__.py
qtree/ctree.py
qtree/data.py
qtree/qtree.py
qtree/quant.py
quantum_tree-1.2.dist-info/LICENSE
quantum_tree-1.2.dist-info/METADATA
quantum_tree-1.2.dist-info/WHEEL
quantum_tree-1.2.dist-info/top_level.txt
quantum_tree-1.2.dist-info/RECORD
