Metadata-Version: 2.1
Name: quantum-tree
Version: 1.2
Summary: Quantum decision trees with binary features and binary classes
Home-page: https://github.com/RaoulHeese/qtree
Download-URL: https://github.com/RaoulHeese/qtree/releases
Author: Raoul Heese
Author-email: raoul.heese@gmail.com
Maintainer: Raoul Heese
Maintainer-email: raoul.heese@gmail.com
License: MIT
Project-URL: Bug Tracker, https://github.com/RaoulHeese/qtree/issues
Project-URL: Source Code, https://github.com/RaoulHeese/qtree
Classifier: License :: OSI Approved :: MIT License
Classifier: Intended Audience :: Science/Research
Classifier: Programming Language :: Python
Classifier: Topic :: Scientific/Engineering :: Artificial Intelligence
Classifier: Topic :: Scientific/Engineering :: Physics
License-File: LICENSE
Requires-Dist: numpy
Requires-Dist: deap
Requires-Dist: scikit-learn
Requires-Dist: qiskit
Requires-Dist: qiskit-aer
